retail_ai/__init__.py
retail_ai/agent_as_code.py
retail_ai/catalog.py
retail_ai/cli.py
retail_ai/config.py
retail_ai/graph.py
retail_ai/guardrails.py
retail_ai/hooks.py
retail_ai/messages.py
retail_ai/models.py
retail_ai/nodes.py
retail_ai/state.py
retail_ai/tools.py
retail_ai/types.py
retail_ai/utils.py
retail_ai/vector_search.py
retail_ai/providers/__init__.py
retail_ai/providers/base.py
retail_ai/providers/databricks.py
retail_ai-0.2.3.dist-info/METADATA
retail_ai-0.2.3.dist-info/WHEEL
retail_ai-0.2.3.dist-info/entry_points.txt
retail_ai-0.2.3.dist-info/licenses/LICENSE
retail_ai-0.2.3.dist-info/RECORD
