Metadata-Version: 2.4
Name: retail-ai
Version: 0.2.3
Summary: Retail AI Agent: A modular, multi-agent orchestration framework for complex AI workflows. Supports agent handoff, tool integration, and dynamic configuration via YAML.
License-File: LICENSE
Requires-Python: >=3.12
Requires-Dist: databricks-agents>=0.20.0
Requires-Dist: databricks-langchain>=0.4.2
Requires-Dist: databricks-sdk>=0.50.0
Requires-Dist: databricks-vectorsearch>=0.56
Requires-Dist: duckduckgo-search>=8.0.2
Requires-Dist: grandalf>=0.8
Requires-Dist: langchain-mcp-adapters>=0.1.4
Requires-Dist: langchain>=0.3.24
Requires-Dist: langgraph-checkpoint-postgres>=2.0.21
Requires-Dist: langgraph-reflection>=0.0.1
Requires-Dist: langgraph-supervisor>=0.0.27
Requires-Dist: langgraph-swarm>=0.0.11
Requires-Dist: langgraph>=0.3.31
Requires-Dist: langmem>=0.0.27
Requires-Dist: loguru>=0.7.3
Requires-Dist: mcp>=1.9.1
Requires-Dist: mlflow>=2.21.3
Requires-Dist: openevals>=0.0.19
Requires-Dist: psycopg[binary,pool]>=3.2.6
Requires-Dist: pydantic>=2.11.3
Requires-Dist: python-dotenv>=1.1.0
Requires-Dist: pyyaml>=6.0.2
Requires-Dist: rich>=14.0.0
Requires-Dist: sqlparse>=0.5.3
Requires-Dist: unitycatalog-ai[databricks]>=0.3.0
